jtime
