Metadata-Version: 1.1
Name: jtime
Version: 0.5.4
Summary: Jira time tracking tool built on the command line to take context from your various git repositories.
Home-page: http://github.com/mapmyfitness/jtime
Author: UNKNOWN
Author-email: UNKNOWN
License: UNKNOWN
Keywords: jira time track command-line
Platform: UNKNOWN
Classifier: Development Status :: 4 - Beta
Classifier: Intended Audience :: Developers
Classifier: Operating System :: OS Independent
Classifier: Programming Language :: Python :: 2.6
Classifier: Programming Language :: Python :: 2.7
Classifier: Topic :: Internet :: WWW/HTTP
